{
  "generated_at": "2026-02-23T01:29:19.096770+08:00",
  "total_titles_processed": 345,
  "failed_sources": [],
  "trends": [
    {
      "keyword_group": "港股 港股通 股市",
      "match_count": 1,
      "titles": [
        {
          "title": "全球资金推动拉丁美洲股市创下历史性强劲开局",
          "url": "https://flash.jin10.com/detail/20260222224916288800",
          "source": "金十数据",
          "ranks": [
            4
          ],
          "is_new": false,
          "appearance_count": 2,
          "time_info": "[00时35分 ~ 01时29分]"
        }
      ]
    }
  ],
  "report_image_url": "https://github.com/Bobobo2025/TrendRadar/img/news.jpg"
}