{
  "generated_at": "2026-02-23T10:28:43.203499+08:00",
  "total_titles_processed": 653,
  "failed_sources": [],
  "trends": [
    {
      "keyword_group": "港股 港股通 股市",
      "match_count": 4,
      "titles": [
        {
          "title": "全球资金推动拉丁美洲股市创下历史性强劲开局",
          "url": "https://flash.jin10.com/detail/20260222224916288800",
          "source": "金十数据",
          "ranks": [
            4,
            5,
            16,
            29
          ],
          "is_new": false,
          "appearance_count": 7,
          "time_info": "[00时35分 ~ 06时28分]"
        },
        {
          "title": "恒生科技指数日内涨幅扩大至3%，美团涨超5%，华虹半导体、中芯国际涨超4%。 港股大模型概念跌幅扩大，智谱跌超17%，MINIMAX跌超11%。",
          "url": "https://wallstreetcn.com/livenews/3057331",
          "source": "华尔街见闻-快讯",
          "ranks": [
            4
          ],
          "is_new": true,
          "appearance_count": 1,
          "time_info": "10时28分"
        },
        {
          "title": "欢迎进入链接网页右侧下载本周财经数据与事件精美周历壁纸：今日港股正常开市，南、北向交易关闭，沪深及北交所、国内期货交易所休市。",
          "url": "https://flash.jin10.com/detail/20260223082822698800",
          "source": "金十数据",
          "ranks": [
            19
          ],
          "is_new": true,
          "appearance_count": 1,
          "time_info": "10时28分"
        },
        {
          "title": "韩国首尔综指高开1.6%。 日本股市因假期休市。",
          "url": "https://wallstreetcn.com/livenews/3057312",
          "source": "华尔街见闻-快讯",
          "ranks": [
            23
          ],
          "is_new": true,
          "appearance_count": 1,
          "time_info": "10时28分"
        }
      ]
    }
  ],
  "report_image_url": "https://github.com/Bobobo2025/TrendRadar/img/news.jpg"
}