{
  "generated_at": "2025-10-24T00:28:56.499729+08:00",
  "total_titles_processed": 315,
  "failed_sources": [],
  "trends": [
    {
      "keyword_group": "港股 港股通 股市",
      "match_count": 3,
      "titles": [
        {
          "title": "一图看懂 | QFII三季度“逛股市”：不挤热门赛道，偏爱“小而美”",
          "url": "https://www.cls.cn/detail/2178501",
          "source": "财联社热门",
          "ranks": [
            6
          ],
          "is_new": false,
          "appearance_count": 1,
          "time_info": "00时28分"
        },
        {
          "title": "英国股市创收盘历史新高",
          "url": "https://wallstreetcn.com/livenews/2992681",
          "source": "华尔街见闻-快讯",
          "ranks": [
            17
          ],
          "is_new": false,
          "appearance_count": 1,
          "time_info": "00时28分"
        },
        {
          "title": "金十图示：2025年10月23日（周四）全球股市指数-欧洲市场（收盘）",
          "url": "https://flash.jin10.com/detail/20251023234144004800",
          "source": "金十数据",
          "ranks": [
            28
          ],
          "is_new": false,
          "appearance_count": 1,
          "time_info": "00时28分"
        }
      ]
    },
    {
      "keyword_group": "小米 小米汽车",
      "match_count": 1,
      "titles": [
        {
          "title": "市监局介入处理小米YU7不明零件",
          "url": "https://m.weibo.cn/search?containerid=100103type%3D1%26t%3D10%26q%3D%23%E5%B8%82%E7%9B%91%E5%B1%80%E4%BB%8B%E5%85%A5%E5%A4%84%E7%90%86%E5%B0%8F%E7%B1%B3YU7%E4%B8%8D%E6%98%8E%E9%9B%B6%E4%BB%B6%23&stream_entry_id=31&isnewpage=1&extparam=seat%3D1%26stream_entry_id%3D31%26q%3D%2523%25E5%25B8%2582%25E7%259B%2591%25E5%25B1%2580%25E4%25BB%258B%25E5%2585%25A5%25E5%25A4%2584%25E7%2590%2586%25E5%25B0%258F%25E7%25B1%25B3YU7%25E4%25B8%258D%25E6%2598%258E%25E9%259B%25B6%25E4%25BB%25B6%2523%26filter_type%3Drealtimehot%26lcate%3D5001%26flag%3D1%26c_type%3D31%26band_rank%3D30%26pos%3D30%26cate%3D5001%26dgr%3D0%26realpos%3D30%26display_time%3D1761236215%26pre_seqid%3D17612362152590115382682",
          "source": "微博",
          "ranks": [
            30
          ],
          "is_new": false,
          "appearance_count": 1,
          "time_info": "00时28分"
        }
      ]
    }
  ],
  "report_image_url": "https://github.com/Bobobo2025/TrendRadar/img/news.jpg"
}